[{"senderKeyId":1137095072,"senderChainKey":{"iteration":385,"seed":"TOJI+qE9Trq0DiKW5WRhA49YAshB7bbYBs9QvVGlbq8="},"senderSigningKey":{"public":"BfksgEB064tROfPpSPWo6aFrZ70cvF3r6ylE/oynvT0x","private":"mFMD9s6NhTZmka8dvMWfHOCnUvhI1ylyEvgEoKvDiH8="},"senderMessageKeys":[{},{},{},{},{},{},{},{},{},{},{},{},{},{},{},{},{},{},{},{},{},{},{},{},{},{},{},{},{},{},{},{},{},{},{},{},{},{},{},{},{},{},{},{},{},{},{},{},{},{},{},{},{},{},{},{},{},{},{},{},{},{},{},{},{},{},{},{},{},{},{},{},{},{},{},{},{},{},{},{},{},{},{},{},{},{},{},{},{},{},{},{},{},{},{},{},{},{},{},{},{},{},{},{},{},{},{},{},{},{},{},{},{},{},{},{},{},{},{},{},{},{},{},{},{},{},{},{},{},{},{},{},{},{},{},{},{},{},{},{},{},{},{},{},{},{},{},{},{},{},{},{},{},{},{},{},{},{},{},{},{},{},{},{},{},{},{},{},{},{},{},{},{},{},{},{},{},{},{},{},{},{},{},{},{},{},{},{},{},{},{},{}]}]